{
  "meta": {
    "desc": "Collection of C++ libraries",
    "desc_long": null,
    "home": "http://boost.org/",
    "license": {
      "deprecated": false,
      "free": true,
      "fullName": "Boost Software License 1.0",
      "redistributable": true,
      "shortName": "boost",
      "spdxId": "BSL-1.0",
      "url": "https://spdx.org/licenses/BSL-1.0.html"
    },
    "maintainers": null
  },
  "versions": [
    {
      "first": "05f8794b0ff7c78df76c3a940dc84f2d2ebbc87e",
      "last": "0535a5b7acf63780716a4442eea2875f4ee2b94f",
      "name": "1.75.0"
    }
  ]
}