{
  "meta": {
    "desc": "BPF based visual packet rate monitor",
    "desc_long": null,
    "home": "https://github.com/bbonev/bpfmon",
    "license": {
      "deprecated": false,
      "free": true,
      "fullName": "GNU General Public License v2.0 or later",
      "redistributable": true,
      "shortName": "gpl2Plus",
      "spdxId": "GPL-2.0-or-later",
      "url": "https://spdx.org/licenses/GPL-2.0-or-later.html"
    },
    "maintainers": [
      {
        "email": "alex@rezvov.ru",
        "github": "arezvov",
        "githubId": 58516559,
        "name": "Alexander Rezvov"
      }
    ]
  },
  "versions": [
    {
      "first": "04f959640594d7770369ab4c7a135dd4674ac945",
      "last": "00460bd6e2c89f3b76dcb42032194e6eed0616d2",
      "name": "2.50"
    }
  ]
}