{
  "meta": {
    "desc": "CLI workflow manager",
    "desc_long": "Corgi is a command-line tool that helps with your repetitive command usages by organizing them into reusable snippet.\n",
    "home": "https://github.com/DrakeW/corgi",
    "license": {
      "deprecated": false,
      "free": true,
      "fullName": "MIT License",
      "redistributable": true,
      "shortName": "mit",
      "spdxId": "MIT",
      "url": "https://spdx.org/licenses/MIT.html"
    },
    "maintainers": [
      {
        "email": "wael.nasreddine@gmail.com",
        "github": "kalbasit",
        "githubId": 87115,
        "matrix": "@kalbasit:matrix.org",
        "name": "Wael Nasreddine"
      }
    ]
  },
  "versions": [
    {
      "first": "003ca4ecd263aaa94c6abaa5cc80904ec8fd6ede",
      "last": "0278e1e297b9862919a66aab312cb1567a1e863d",
      "name": ""
    }
  ]
}