{
  "meta": {
    "desc": "Chess program developed by Dr. Robert M. Hyatt",
    "desc_long": null,
    "home": "http://www.craftychess.com/",
    "license": {
      "deprecated": false,
      "free": false,
      "fullName": "Unfree",
      "redistributable": false,
      "shortName": "unfree"
    },
    "maintainers": [
      {
        "email": "johnw@newartisans.com",
        "github": "jwiegley",
        "githubId": 8460,
        "name": "John Wiegley"
      }
    ]
  },
  "versions": [
    {
      "commits": [
        {
          "first": "045e1332d97d0db7c09265d2c2041fbca906286c",
          "last": "00460bd6e2c89f3b76dcb42032194e6eed0616d2"
        }
      ],
      "name": "25.0.1"
    }
  ]
}