{
  "meta": {
    "desc": "GameNetworkingSockets is a basic transport layer for games",
    "desc_long": null,
    "home": "https://github.com/ValveSoftware/GameNetworkingSockets",
    "license": {
      "deprecated": false,
      "free": true,
      "fullName": "BSD 3-clause \"New\" or \"Revised\" License",
      "redistributable": true,
      "shortName": "bsd3",
      "spdxId": "BSD-3-Clause",
      "url": "https://spdx.org/licenses/BSD-3-Clause.html"
    },
    "maintainers": [
      {
        "email": "sternenseemann@systemli.org",
        "github": "sternenseemann",
        "githubId": 3154475,
        "name": "Lukas Epple"
      }
    ]
  },
  "versions": [
    {
      "commits": [
        {
          "first": "07f5e909b2356a64b5304717eda6710580bdc162",
          "last": "06708435d1c6527b5119daafe9c96df9968cf3a6"
        }
      ],
      "name": "1.2.0"
    }
  ]
}