{
  "meta": {
    "desc": "Screen reader",
    "desc_long": "A free, open source, flexible and extensible screen reader that provides\naccess to the graphical desktop via speech and refreshable braille.\nIt works with applications and toolkits that support the Assistive\nTechnology Service Provider Interface (AT-SPI). That includes the GNOME\nGTK toolkit, the Java platform's Swing toolkit, LibreOffice, Gecko, and\nWebKitGtk. AT-SPI support for the KDE Qt toolkit is being pursued.\n\nNeeds `services.gnome.at-spi2-core.enable = true;` in `configuration.nix`.\n",
    "home": "https://wiki.gnome.org/Projects/Orca",
    "license": {
      "deprecated": true,
      "free": true,
      "fullName": "GNU Lesser General Public License v2.1",
      "redistributable": true,
      "shortName": "lgpl21",
      "spdxId": "LGPL-2.1",
      "url": "https://spdx.org/licenses/LGPL-2.1.html"
    },
    "maintainers": [
      {
        "email": "bert.moens@gmail.com",
        "github": "berce",
        "githubId": 10439709,
        "name": "Bert Moens"
      },
      {
        "email": "torhedinbronner@gmail.com",
        "github": "hedning",
        "githubId": 71978,
        "name": "Tor Hedin Br\u00f8nner"
      },
      {
        "email": "jtojnar@gmail.com",
        "github": "jtojnar",
        "githubId": 705123,
        "matrix": "@jtojnar:matrix.org",
        "name": "Jan Tojnar"
      },
      {
        "email": "daniel@serbanescu.dk",
        "github": "dasj19",
        "githubId": 7589338,
        "name": "Daniel \u0218erb\u0103nescu"
      },
      {
        "email": "maxeaubrey@gmail.com",
        "github": "maxeaubrey",
        "githubId": 35892750,
        "name": "Maxine Aubrey"
      }
    ]
  },
  "versions": [
    {
      "first": "038152e4ee26bb81d1ffff59260e1183a1b735da",
      "last": "02ac19b524467e1de5b1efb3853a496b936f8df2",
      "name": "41.0"
    },
    {
      "first": "023ba7668927e9b964dddde6681e70396e223a47",
      "last": "023ba7668927e9b964dddde6681e70396e223a47",
      "name": "40.0"
    },
    {
      "first": "03bd5499af8a3d6b3b91714be7280b94ffb10903",
      "last": "02e4d8ce5b58e1475675defdb0f80a333f4e5a85",
      "name": "41.0"
    },
    {
      "first": "0242265e551d0ea9f674bf771065f353f780b1a5",
      "last": "0242265e551d0ea9f674bf771065f353f780b1a5",
      "name": "40.0"
    },
    {
      "first": "01031cec26bf9cda82336f1cb97ac59be533a4b0",
      "last": "01031cec26bf9cda82336f1cb97ac59be533a4b0",
      "name": "41.0"
    },
    {
      "first": "03aa75f46d14e3323d03262ca424b2e7f0aab99c",
      "last": "01478aefb3935b463849bc5e64af367a468538a7",
      "name": "40.0"
    }
  ]
}