{
  "meta": {
    "desc": "The `hibernate' script for swsusp and Tux-on-Ice",
    "desc_long": "This package provides the `hibernate' script, a command-line utility\nthat saves the computer's state to disk and switches it off, turning\nit into \"hibernation\".  It works both with Linux swsusp and Tux-on-Ice.\n",
    "home": "http://www.tuxonice.net/",
    "license": {
      "deprecated": false,
      "free": true,
      "fullName": "GNU General Public License v2.0 or later",
      "redistributable": true,
      "shortName": "gpl2Plus",
      "spdxId": "GPL-2.0-or-later",
      "url": "https://spdx.org/licenses/GPL-2.0-or-later.html"
    },
    "maintainers": null
  },
  "versions": [
    {
      "first": "05fcd91c57cfcdd7382628cd81a67b1ccdda699a",
      "last": "0704a1b7dd4e0bc564f5798ad32b3dfb5eeaeca9",
      "name": "2.0"
    },
    {
      "first": "0686eecf4f27f578b510374833625db6a0a51ef5",
      "last": "06fe4d9904e7b79f8b2cd94761237b72431acc62",
      "name": "1.98.1"
    }
  ]
}