{
  "meta": {
    "desc": "A multiplatform free hamradio logger",
    "desc_long": "KLog provides QSO management, useful QSL management DX-Cluster client, DXCC management,\nClubLog integration, WSJT-X, DX-Marathon support and much more.\n",
    "home": "https://www.klog.xyz/",
    "license": {
      "deprecated": false,
      "free": true,
      "fullName": "GNU General Public License v2.0 or later",
      "redistributable": true,
      "shortName": "gpl2Plus",
      "spdxId": "GPL-2.0-or-later",
      "url": "https://spdx.org/licenses/GPL-2.0-or-later.html"
    },
    "maintainers": [
      {
        "email": "1838397+pulsation@users.noreply.github.com",
        "github": "pulsation",
        "githubId": 1838397,
        "name": "Philippe Sam-Long"
      }
    ]
  },
  "versions": [
    {
      "first": "049322de7cc036fa548c2ae2861e97c1dd9fa855",
      "last": "00460bd6e2c89f3b76dcb42032194e6eed0616d2",
      "name": "1.3.2"
    }
  ]
}