{
  "meta": {
    "desc": "Kuma service mesh controller",
    "desc_long": null,
    "home": "https://kuma.io/",
    "license": {
      "deprecated": false,
      "free": true,
      "fullName": "Apache License 2.0",
      "redistributable": true,
      "shortName": "asl20",
      "spdxId": "Apache-2.0",
      "url": "https://spdx.org/licenses/Apache-2.0.html"
    },
    "maintainers": [
      {
        "email": "zbioe@protonmail.com",
        "github": "zbioe",
        "githubId": 7332055,
        "name": "Iury Fukuda"
      },
      {
        "email": "wael.nasreddine@gmail.com",
        "github": "kalbasit",
        "githubId": 87115,
        "matrix": "@kalbasit:matrix.org",
        "name": "Wael Nasreddine"
      }
    ]
  },
  "versions": [
    {
      "commits": [
        {
          "first": "07ea60c42397b170b342343f9183fb6a12c07117",
          "last": "00460bd6e2c89f3b76dcb42032194e6eed0616d2"
        }
      ],
      "name": "1.3.1"
    }
  ]
}