{
  "meta": {
    "desc": "A C++ library to access PostgreSQL databases",
    "desc_long": null,
    "home": "http://pqxx.org/development/libpqxx/",
    "license": {
      "deprecated": false,
      "free": true,
      "fullName": "BSD 3-clause \"New\" or \"Revised\" License",
      "redistributable": true,
      "shortName": "bsd3",
      "spdxId": "BSD-3-Clause",
      "url": "https://spdx.org/licenses/BSD-3-Clause.html"
    },
    "maintainers": [
      {
        "email": "edolstra+nixpkgs@gmail.com",
        "github": "edolstra",
        "githubId": 1148549,
        "name": "Eelco Dolstra"
      }
    ]
  },
  "versions": [
    {
      "first": "00cba5e8e7d65977c38a8a78f9271ed23473b433",
      "last": "020738a1fb53c0123a9a4ebd578106aa04d3ac21",
      "name": "6.4.5"
    }
  ]
}