{
  "meta": {
    "desc": "A network transparent, client/server audio transport system",
    "desc_long": null,
    "home": "http://radscan.com/nas.html",
    "license": {
      "deprecated": false,
      "free": true,
      "fullName": "MIT License",
      "redistributable": true,
      "shortName": "mit",
      "spdxId": "MIT",
      "url": "https://spdx.org/licenses/MIT.html"
    },
    "maintainers": []
  },
  "versions": [
    {
      "commits": [
        {
          "first": "05e9c47dc3c164417803ec9c769043da7575d5f5",
          "last": "065281add0016f2c1e6fa340ae78823fba9124c7"
        }
      ],
      "name": "1.9.4"
    }
  ]
}