{
  "meta": {
    "desc": "A tool for performing one-way active measurements",
    "desc_long": null,
    "home": "http://software.internet2.edu/owamp/",
    "license": {
      "deprecated": false,
      "free": true,
      "fullName": "Apache License 2.0",
      "redistributable": true,
      "shortName": "asl20",
      "spdxId": "Apache-2.0",
      "url": "https://spdx.org/licenses/Apache-2.0.html"
    },
    "maintainers": [
      {
        "email": "mcoudron@hotmail.com",
        "github": "teto",
        "githubId": 886074,
        "name": "Matthieu Coudron"
      }
    ]
  },
  "versions": [
    {
      "first": "01d7e7df2aa4da897341ec9d6e86e711c7a1a607",
      "last": "045fe2465cacb7d91a623c6d01daf07ecc28e17b",
      "name": "3.5.6"
    }
  ]
}