{
  "meta": {
    "desc": "A python library built to easily handle data structure such are lists, trees and acyclic graphs",
    "desc_long": null,
    "home": "https://github.com/getting-things-gnome/liblarch",
    "license": {
      "deprecated": false,
      "free": true,
      "fullName": "GNU Lesser General Public License v3.0 or later",
      "redistributable": true,
      "shortName": "lgpl3Plus",
      "spdxId": "LGPL-3.0-or-later",
      "url": "https://spdx.org/licenses/LGPL-3.0-or-later.html"
    },
    "maintainers": [
      {
        "email": "m.scheuren@oyra.eu",
        "github": "oyren",
        "githubId": 15930073,
        "name": "Moritz Scheuren"
      }
    ]
  },
  "versions": [
    {
      "first": "059675cd0de0616e42081d85a972da0f09b676cd",
      "last": "04a15518c1a1fe06663e4d18d610ccd983c6fa6a",
      "name": "3.0.1"
    }
  ]
}