{
  "meta": {
    "desc": "DKIM + ARC email signing/verification tools + Python module",
    "desc_long": "Python module that implements DKIM (DomainKeys Identified Mail) email\nsigning and verification. It also provides a number of conv\u0454nient tools\nfor command line signing and verification, as well as generating new DKIM\nrecords. This version also supports the experimental Authenticated\nReceived Chain (ARC) protocol.\n",
    "home": "https://launchpad.net/dkimpy",
    "license": {
      "deprecated": false,
      "free": true,
      "fullName": "BSD 3-clause \"New\" or \"Revised\" License",
      "redistributable": true,
      "shortName": "bsd3",
      "spdxId": "BSD-3-Clause",
      "url": "https://spdx.org/licenses/BSD-3-Clause.html"
    },
    "maintainers": [
      {
        "email": "ml.software@leenaa.rs",
        "github": "leenaars",
        "githubId": 4158274,
        "name": "Michiel Leenaars"
      }
    ]
  },
  "outputs": {
    "out": [
      "/bin/.arcsign-wrapped",
      "/bin/.arcverify-wrapped",
      "/bin/.dkimsign-wrapped",
      "/bin/.dkimverify-wrapped",
      "/bin/.dknewkey-wrapped",
      "/bin/arcsign",
      "/bin/arcverify",
      "/bin/dkimsign",
      "/bin/dkimverify",
      "/bin/dknewkey",
      "/lib/python3.9/site-packages/dkim/__init__.py",
      "/lib/python3.9/site-packages/dkim/__main__.py",
      "/lib/python3.9/site-packages/dkim/__pycache__/__init__.cpython-39.pyc",
      "/lib/python3.9/site-packages/dkim/__pycache__/__main__.cpython-39.pyc",
      "/lib/python3.9/site-packages/dkim/__pycache__/arcsign.cpython-39.pyc",
      "/lib/python3.9/site-packages/dkim/__pycache__/arcverify.cpython-39.pyc",
      "/lib/python3.9/site-packages/dkim/__pycache__/asn1.cpython-39.pyc",
      "/lib/python3.9/site-packages/dkim/__pycache__/asyncsupport.cpython-39.pyc",
      "/lib/python3.9/site-packages/dkim/__pycache__/canonicalization.cpython-39.pyc",
      "/lib/python3.9/site-packages/dkim/__pycache__/crypto.cpython-39.pyc",
      "/lib/python3.9/site-packages/dkim/__pycache__/dkimsign.cpython-39.pyc",
      "/lib/python3.9/site-packages/dkim/__pycache__/dkimverify.cpython-39.pyc",
      "/lib/python3.9/site-packages/dkim/__pycache__/dknewkey.cpython-39.pyc",
      "/lib/python3.9/site-packages/dkim/__pycache__/dnsplug.cpython-39.pyc",
      "/lib/python3.9/site-packages/dkim/__pycache__/util.cpython-39.pyc",
      "/lib/python3.9/site-packages/dkim/arcsign.py",
      "/lib/python3.9/site-packages/dkim/arcverify.py",
      "/lib/python3.9/site-packages/dkim/asn1.py",
      "/lib/python3.9/site-packages/dkim/asyncsupport.py",
      "/lib/python3.9/site-packages/dkim/canonicalization.py",
      "/lib/python3.9/site-packages/dkim/crypto.py",
      "/lib/python3.9/site-packages/dkim/dkimsign.py",
      "/lib/python3.9/site-packages/dkim/dkimverify.py",
      "/lib/python3.9/site-packages/dkim/dknewkey.py",
      "/lib/python3.9/site-packages/dkim/dnsplug.py",
      "/lib/python3.9/site-packages/dkim/util.py",
      "/lib/python3.9/site-packages/dkimpy-1.0.5.dist-info/INSTALLER",
      "/lib/python3.9/site-packages/dkimpy-1.0.5.dist-info/LICENSE",
      "/lib/python3.9/site-packages/dkimpy-1.0.5.dist-info/METADATA",
      "/lib/python3.9/site-packages/dkimpy-1.0.5.dist-info/RECORD",
      "/lib/python3.9/site-packages/dkimpy-1.0.5.dist-info/REQUESTED",
      "/lib/python3.9/site-packages/dkimpy-1.0.5.dist-info/WHEEL",
      "/lib/python3.9/site-packages/dkimpy-1.0.5.dist-info/direct_url.json",
      "/lib/python3.9/site-packages/dkimpy-1.0.5.dist-info/entry_points.txt",
      "/lib/python3.9/site-packages/dkimpy-1.0.5.dist-info/top_level.txt",
      "/nix-support/propagated-build-inputs",
      "/share/man/man1/arcsign.1.gz",
      "/share/man/man1/arcverify.1.gz",
      "/share/man/man1/dkimsign.1.gz",
      "/share/man/man1/dkimverify.1.gz",
      "/share/man/man1/dknewkey.1.gz"
    ]
  },
  "versions": [
    {
      "first": "02ac13b563c082eaa51e8acdbe492a7961231836",
      "last": "02dfbde63938f077e21d7880781132ea141b0b21",
      "name": "1.0.5"
    }
  ]
}