{
  "meta": {
    "desc": "Python utils and helpers library for Gradient",
    "desc_long": null,
    "home": "https://github.com/Paperspace/gradient-utils",
    "license": {
      "deprecated": false,
      "free": true,
      "fullName": "MIT License",
      "redistributable": true,
      "shortName": "mit",
      "spdxId": "MIT",
      "url": "https://spdx.org/licenses/MIT.html"
    },
    "maintainers": [
      {
        "email": "freezeboy@users.noreply.github.com",
        "github": "freezeboy",
        "githubId": 13279982,
        "name": "freezeboy"
      }
    ]
  },
  "versions": [
    {
      "first": "01faf36c520ed7363a280880ef9d6ce70eb05b1f",
      "last": "045fe2465cacb7d91a623c6d01daf07ecc28e17b",
      "name": "0.3.2"
    }
  ]
}