{
  "meta": {
    "desc": "GPU-based tor hidden service name generator",
    "desc_long": null,
    "home": "https://github.com/lachesis/scallion",
    "license": {
      "deprecated": false,
      "free": true,
      "fullName": "MIT License",
      "redistributable": true,
      "shortName": "mit",
      "spdxId": "MIT",
      "url": "https://spdx.org/licenses/MIT.html"
    },
    "maintainers": [
      {
        "email": "jaroslavas@volth.com",
        "github": "volth",
        "githubId": 508305,
        "name": "Jaroslavas Pocepko"
      }
    ]
  },
  "versions": [
    {
      "first": "02dfbab3bed6c1a2acf594c3245baada7e4ed6d1",
      "last": "02dfbde63938f077e21d7880781132ea141b0b21",
      "name": "2.1"
    }
  ]
}