{
  "meta": {
    "desc": "A Nintendo 64 segment assembler",
    "desc_long": "An open-source version of the Nintendo64 sdk's mild.exe. Assembles\nsegments into an n64-compatible rom.\n",
    "home": "https://github.com/trhodeos/spicy",
    "license": {
      "deprecated": false,
      "free": true,
      "fullName": "MIT License",
      "redistributable": true,
      "shortName": "mit",
      "spdxId": "MIT",
      "url": "https://spdx.org/licenses/MIT.html"
    },
    "maintainers": [
      {
        "email": "owen@owen.cafe",
        "github": "414owen",
        "githubId": 1714287,
        "name": "Owen Shepherd"
      }
    ]
  },
  "versions": [
    {
      "first": "0263ae262acb431e701afaa95f5c10b196419496",
      "last": "00460bd6e2c89f3b76dcb42032194e6eed0616d2",
      "name": "2020-02-21"
    }
  ]
}