{
  "meta": {
    "desc": "An implementation of the BitTorrent protocol that is optimised for streaming media",
    "desc_long": null,
    "home": "https://github.com/jech/storrent",
    "license": {
      "deprecated": false,
      "free": true,
      "fullName": "MIT License",
      "redistributable": true,
      "shortName": "mit",
      "spdxId": "MIT",
      "url": "https://spdx.org/licenses/MIT.html"
    },
    "maintainers": [
      {
        "email": "marsam@users.noreply.github.com",
        "github": "marsam",
        "githubId": 65531,
        "name": "Mario Rodas"
      },
      {
        "email": "wael.nasreddine@gmail.com",
        "github": "kalbasit",
        "githubId": 87115,
        "matrix": "@kalbasit:matrix.org",
        "name": "Wael Nasreddine"
      }
    ]
  },
  "versions": [
    {
      "first": "019044d229455a819564a62f5d172da881d934e3",
      "last": "02ac19b524467e1de5b1efb3853a496b936f8df2",
      "name": "2021-10-10"
    }
  ]
}