{
  "meta": {
    "desc": "A program that can validate your HTML, as well as modify it to be more clean and standard",
    "desc_long": null,
    "home": "http://tidyp.com/",
    "license": {
      "deprecated": false,
      "free": true,
      "fullName": "BSD 3-clause \"New\" or \"Revised\" License",
      "redistributable": true,
      "shortName": "bsd3",
      "spdxId": "BSD-3-Clause",
      "url": "https://spdx.org/licenses/BSD-3-Clause.html"
    },
    "maintainers": [
      {
        "email": "mail@pascal-wittmann.de",
        "github": "pSub",
        "githubId": 83842,
        "name": "Pascal Wittmann"
      }
    ]
  },
  "versions": [
    {
      "first": "0310a61e66fd469c04d4c30f24d63c2a0e4c6002",
      "last": "0278e1e297b9862919a66aab312cb1567a1e863d",
      "name": "1.04"
    }
  ]
}