{
  "meta": {
    "desc": "Universal Aggregator",
    "desc_long": null,
    "home": "https://github.com/sloonz/ua",
    "license": {
      "deprecated": false,
      "free": true,
      "fullName": "ISC License",
      "redistributable": true,
      "shortName": "isc",
      "spdxId": "ISC",
      "url": "https://spdx.org/licenses/ISC.html"
    },
    "maintainers": [
      {
        "email": "ttuegel@mailbox.org",
        "github": "ttuegel",
        "githubId": 563054,
        "name": "Thomas Tuegel"
      }
    ]
  },
  "versions": [
    {
      "first": "03942659ca1189ba50f9f1b86bbe6d925eba237b",
      "last": "04a15518c1a1fe06663e4d18d610ccd983c6fa6a",
      "name": "2017-02-24"
    }
  ]
}