{
  "meta": {
    "desc": null,
    "desc_long": null,
    "home": null,
    "license": {
      "deprecated": false,
      "free": true,
      "fullName": "MIT License",
      "redistributable": true,
      "shortName": "mit",
      "spdxId": "MIT",
      "url": "https://spdx.org/licenses/MIT.html"
    },
    "maintainers": null
  },
  "versions": [
    {
      "commits": [
        {
          "first": "00305cca18fbaef088f87362350839929f0e42c5",
          "last": "065281add0016f2c1e6fa340ae78823fba9124c7"
        }
      ],
      "name": "4.12.11"
    }
  ]
}